plugs_auth/__init__.py
plugs_auth/admin.py
plugs_auth/decorators.py
plugs_auth/emails.py
plugs_auth/managers.py
plugs_auth/models.py
plugs_auth/runtests.py
plugs_auth/serializers.py
plugs_auth/settings.py
plugs_auth/utils.py
plugs_auth/views.py
plugs_auth/templates/emails/account_activated_en.html
plugs_auth/templates/emails/account_activated_pt.html
plugs_auth/templates/emails/activate_account_en.html
plugs_auth/templates/emails/activate_account_pt.html
plugs_auth/templates/emails/reset_password_en.html
plugs_auth/templates/emails/reset_password_pt.html
plugs_auth-0.2.3.dist-info/AUTHORS.rst
plugs_auth-0.2.3.dist-info/LICENSE
plugs_auth-0.2.3.dist-info/METADATA
plugs_auth-0.2.3.dist-info/WHEEL
plugs_auth-0.2.3.dist-info/top_level.txt
plugs_auth-0.2.3.dist-info/RECORD
