Metadata-Version: 2.1
Name: plugs-auth
Version: 0.2.3
Summary: Reusable Authentication
Home-page: https://github.com/solocompt/plugs-auth
Author: Solo
Author-email: geral@solo.com.pt
License: MIT
Keywords: plugs-auth
Platform: UNKNOWN
Classifier: Development Status :: 3 - Alpha
Classifier: Framework :: Django :: 1.11
Classifier: Intended Audience :: Developers
Classifier: License :: OSI Approved :: MIT License
Classifier: Natural Language :: English
Classifier: Programming Language :: Python :: 3
Requires-Dist: plugs-core (>=0.2.0)
Requires-Dist: plugs-mail (>=0.2.0)
